[{"line":2,"elements":[{"start_timestamp":"2023-05-15T14:30:47.074Z","before":[{"result":{"duration":2530144800,"status":"passed"},"match":{"location":"step_definitions.api_steps.Hooks.retrieveToken(io.cucumber.java.Scenario)"}}],"line":71,"name":"Add a new course to the database","description":"","id":"perform-a-request-for-verifying-course-data-for-sdet-and-dev;add-a-new-course-to-the-database","type":"scenario","keyword":"Scenario","steps":[{"result":{"duration":2000100,"status":"passed"},"line":72,"name":"the \"Dev\" course endpoint is \"https://tla-school-api.herokuapp.com/api/school/programs/devcourse\"","match":{"arguments":[{"val":"\"Dev\"","offset":4},{"val":"\"https://tla-school-api.herokuapp.com/api/school/programs/devcourse\"","offset":29}],"location":"step_definitions.api_steps.Api_StepDefinitions.theSDETCourseEndpointIs(java.lang.String,java.lang.String)"},"keyword":"Given "},{"result":{"duration":758043400,"status":"passed"},"line":73,"name":"I send a POST request to the Dev course endpoint to add the course","match":{"location":"step_definitions.api_steps.Api_StepDefinitions.iSendAPOSTRequestToTheDevCourseEndpointToAddTheCourse()"},"keyword":"When "},{"result":{"duration":4000200,"status":"passed"},"line":74,"name":"the response status code is 200","match":{"arguments":[{"val":"200","offset":28}],"location":"step_definitions.api_steps.Api_StepDefinitions.theResponseStatusCodeIs(int)"},"keyword":"Then "},{"result":{"duration":5000300,"status":"passed"},"line":75,"name":"the response body contains the following fields:","match":{"location":"step_definitions.api_steps.Api_StepDefinitions.theResponseBodyContainsTheFollowingFields(java.util.List<java.lang.String>)"},"rows":[{"cells":["id"]},{"cells":["name"]},{"cells":["duration"]}],"keyword":"And "}],"tags":[{"name":"@api"},{"name":"@AS-21"}]},{"start_timestamp":"2023-05-15T14:30:50.426Z","before":[{"result":{"duration":394022500,"status":"passed"},"match":{"location":"step_definitions.api_steps.Hooks.retrieveToken(io.cucumber.java.Scenario)"}}],"line":81,"name":"Add a new course to the database","description":"","id":"perform-a-request-for-verifying-course-data-for-sdet-and-dev;add-a-new-course-to-the-database","type":"scenario","keyword":"Scenario","steps":[{"result":{"duration":1000000,"status":"passed"},"line":82,"name":"the \"SDET\" course endpoint is \"https://tla-school-api.herokuapp.com/api/school/programs/sdetcourse\"","match":{"arguments":[{"val":"\"SDET\"","offset":4},{"val":"\"https://tla-school-api.herokuapp.com/api/school/programs/sdetcourse\"","offset":30}],"location":"step_definitions.api_steps.Api_StepDefinitions.theSDETCourseEndpointIs(java.lang.String,java.lang.String)"},"keyword":"Given "},{"result":{"duration":792045300,"status":"passed"},"line":83,"name":"I send a POST request to the SDET course endpoint to add the course","match":{"location":"step_definitions.api_steps.Api_StepDefinitions.iSendAPOSTRequestToTheSDETCourseEndpointToAddTheCourse()"},"keyword":"When "},{"result":{"duration":2000200,"status":"passed"},"line":84,"name":"the response status code is 200","match":{"arguments":[{"val":"200","offset":28}],"location":"step_definitions.api_steps.Api_StepDefinitions.theResponseStatusCodeIs(int)"},"keyword":"Then "},{"result":{"duration":1000100,"status":"passed"},"line":85,"name":"the response body contains the following fields:","match":{"location":"step_definitions.api_steps.Api_StepDefinitions.theResponseBodyContainsTheFollowingFields(java.util.List<java.lang.String>)"},"rows":[{"cells":["id"]},{"cells":["name"]},{"cells":["duration"]}],"keyword":"And "}],"tags":[{"name":"@api"},{"name":"@AS-21"}]}],"name":"perform a request for verifying course data for SDET and Dev","description":"","id":"perform-a-request-for-verifying-course-data-for-sdet-and-dev","keyword":"Feature","uri":"file:src/test/resources/api_features/api.feature","tags":[{"name":"@api","type":"Tag","location":{"line":1,"column":1}}]}]